[
  {
    "id": "A.8.1",
    "title": "Учёт активов",
    "description": "Ведётся ли актуальный реестр информационных активов, включая данные, устройства и сервисы?"
  },
  {
    "id": "A.8.2",
    "title": "Классификация информации",
    "description": "Определены ли уровни конфиденциальности информации и применяются ли соответствующие меры защиты?"
  },
  {
    "id": "A.8.3",
    "title": "Обработка информации",
    "description": "Используются ли утверждённые процедуры для обработки, передачи и хранения информации?"
  },
  {
    "id": "A.8.7",
    "title": "Защита от вредоносного ПО",
    "description": "Используются ли механизмы антивирусной защиты, обновления сигнатур и контроль запускаемых программ?"
  },
  {
    "id": "A.8.8",
    "title": "Управление техническими уязвимостями",
    "description": "Проводится ли регулярное сканирование уязвимостей и устанавливаются ли обновления безопасности?"
  },
  {
    "id": "A.8.9",
    "title": "Управление конфигурациями",
    "description": "Документируются ли настройки систем, включая параметры безопасности, и осуществляется ли их контроль?"
  },
  {
    "id": "A.8.10",
    "title": "Шифрование информации",
    "description": "Применяется ли шифрование к конфиденциальной информации в передаче и хранении?"
  },
  {
    "id": "A.8.11",
    "title": "Управление носителями информации",
    "description": "Установлены ли правила работы с USB-накопителями, внешними дисками и бумажными носителями?"
  },
  {
    "id": "A.8.15",
    "title": "Ведение журналов безопасности",
    "description": "Осуществляется ли централизованный сбор логов и анализ событий безопасности?"
  }
]
